{
  "ProductCollection": [
    {
      "ProductId": "HT-1000",
      "Category": "LT",
      "MainCategory": "Computer Systems",
      "SupplierName": "Very Best Screens",
      "Weight": "4.2",
      "WeightUnit": "KG",
      "ShortDescription": "Notebook Basic 15 with 2,80 GHz quad core, 15\" LCD, 4 GB DDR3 RAM, 500 GB Hard Disc, Windows 8 Pro",
      "Name": "Notebook Basic 15",
      "PictureUrl": "sap/ui/demo/mock/images/HT-1000.jpg",
      "Status": "A",
      "Price": 956,
      "DimensionWidth": "30",
      "DimensionDepth": "18",
      "DimensionHeight": "3",
      "Unit": "cm",
      "CurrencyCode": "EUR"
    },
    {
      "ProductId": "HT-1001",
      "Category": "LT",
      "MainCategory": "Computer Systems",
      "SupplierName": "Very Best Screens",
      "Weight": "4.5",
      "WeightUnit": "KG",
      "ShortDescription": "Notebook Basic 17 with 2,80 GHz quad core, 17\" LCD, 4 GB DDR3 RAM, 500 GB Hard Disc, Windows 8 Pro",
      "Name": "Notebook Basic 17",
      "PictureUrl": "sap/ui/demo/mock/images/HT-1001.jpg",
      "Status": "A",
      "Price": 1249,
      "DimensionWidth": "29",
      "DimensionDepth": "17",
      "DimensionHeight": "3.1",
      "Unit": "cm",
      "CurrencyCode": "EUR"
    },
    {
      "ProductId": "HT-1002",
      "Category": "LT",
      "MainCategory": "Computer Systems",
      "SupplierName": "Very Best Screens",
      "Weight": "4.2",
      "WeightUnit": "KG",
      "ShortDescription": "Notebook Basic 18 with 2,80 GHz quad core, 18\" LCD, 8 GB DDR3 RAM, 1000 GB Hard Disc, Windows 8 Pro",
      "Name": "Notebook Basic 18",
      "PictureUrl": "sap/ui/demo/mock/images/HT-1002.jpg",
      "Status": "A",
      "Price": 1570,
      "DimensionWidth": "28",
      "DimensionDepth": "19",
      "DimensionHeight": "2.5",
      "Unit": "cm",
      "CurrencyCode": "EUR"
    },
    {
      "ProductId": "HT-1003",
      "Category": "LT",
      "MainCategory": "Computer Systems",
      "SupplierName": "Smartcards",
      "Weight": "4.2",
      "WeightUnit": "KG",
      "ShortDescription": "Notebook Basic 19 with 2,80 GHz quad core, 19\" LCD, 8 GB DDR3 RAM, 1000 GB Hard Disc, Windows 8 Pro",
      "Name": "Notebook Basic 19",
      "PictureUrl": "sap/ui/demo/mock/images/HT-1003.jpg",
      "Status": "A",
      "Price": 1650,
      "DimensionWidth": "32",
      "DimensionDepth": "21",
      "DimensionHeight": "4",
      "Unit": "cm",
      "CurrencyCode": "EUR"
    }
  ]
}